MANIFEST.in
README.md
requirements.txt
setup.py
EMbuilder.egg-info/PKG-INFO
EMbuilder.egg-info/SOURCES.txt
EMbuilder.egg-info/dependency_links.txt
EMbuilder.egg-info/top_level.txt
embuilder/__init__.py
embuilder/builder.py
embuilder/main.py
test/test.py